assets/styles.css
doopass/__init__.py
doopass/core/__init__.py
doopass/core/app.py
doopass/core/components/__init__.py
doopass/core/components/backup_manage_menu.py
doopass/core/components/login_page.py
doopass/core/components/login_page_container.py
doopass/core/components/message.py
doopass/core/components/pair_handle_page.py
doopass/core/components/select_menu.py
doopass/core/components/settings_handle_page.py
doopass/core/components/settings_pairs_list.py
doopass/core/components/signup_page.py
doopass/core/components/store_handle_menu.py
doopass/core/components/store_handle_menu_item.py
doopass/core/exceptions.py
doopass/core/logo.py
doopass/core/password_validation.py
doopass/core/screens/__init__.py
doopass/core/screens/backup_manage_screen.py
doopass/core/screens/help_screen.py
doopass/core/screens/login_screen.py
doopass/core/screens/main_menu_screen.py
doopass/core/screens/main_screen.py
doopass/core/screens/message_screen.py
doopass/core/screens/screen.py
doopass/core/screens/settings_pair_handle_screen.py
doopass/core/screens/settings_screen.py
doopass/core/screens/sign_up_screen.py
doopass/core/screens/store_handle_screen.py
doopass/core/screens/store_pair_handle_screen.py
doopass/core/settings.py
doopass/core/store.py
doopass/core/store_backup.py
doopass/doopass.py
doopass/tests/__init__.py
doopass/tests/settings_test.py
doopass-2.9.dist-info/LICENSE
doopass-2.9.dist-info/METADATA
doopass-2.9.dist-info/WHEEL
doopass-2.9.dist-info/entry_points.txt
doopass-2.9.dist-info/RECORD
