Metadata-Version: 2.1
Name: doopass
Version: 2.9
Summary: Crossplatform TUI password manager written in python
Home-page: https://github.com/doopath/PasswordManager
Author: Michael Nikishov
Author-email: doopath@gmail.com
Requires-Python: >=3.12.0,<4.0.0
Classifier: Programming Language :: Python :: 3
Classifier: Programming Language :: Python :: 3.12
Requires-Dist: CacheControl (==0.14.0)
Requires-Dist: Pygments (==2.18.0)
Requires-Dist: SecretStorage (==3.3.3)
Requires-Dist: build (==1.2.1)
Requires-Dist: certifi (==2024.2.2)
Requires-Dist: cffi (==1.16.0)
Requires-Dist: charset-normalizer (==3.3.2)
Requires-Dist: cleo (==2.1.0)
Requires-Dist: crashtest (==0.4.1)
Requires-Dist: cryptography (==42.0.7)
Requires-Dist: distlib (==0.3.8)
Requires-Dist: dulwich (==0.21.7)
Requires-Dist: fastjsonschema (==2.19.1)
Requires-Dist: filelock (==3.14.0)
Requires-Dist: idna (==3.7)
Requires-Dist: installer (==0.7.0)
Requires-Dist: jaraco_classes (==3.4.0)
Requires-Dist: jeepney (==0.8.0)
Requires-Dist: keyring (==24.3.1)
Requires-Dist: linkify-it-py (==2.0.3)
Requires-Dist: markdown-it-py (==3.0.0)
Requires-Dist: mdit-py-plugins (==0.4.1)
Requires-Dist: mdurl (==0.1.2)
Requires-Dist: more-itertools (==10.2.0)
Requires-Dist: msgpack (==1.0.8)
Requires-Dist: packaging (==24.0)
Requires-Dist: pexpect (==4.9.0)
Requires-Dist: pkginfo (==1.10.0)
Requires-Dist: platformdirs (==4.2.2)
Requires-Dist: poetry (==1.8.3)
Requires-Dist: poetry-core (==1.9.0)
Requires-Dist: poetry-plugin-export (==1.8.0)
Requires-Dist: ptyprocess (==0.7.0)
Requires-Dist: pycparser (==2.22)
Requires-Dist: pyperclip (==1.8.2)
Requires-Dist: pyproject_hooks (==1.1.0)
Requires-Dist: rapidfuzz (==3.9.1)
Requires-Dist: requests (==2.32.2)
Requires-Dist: requests-toolbelt (==1.0.0)
Requires-Dist: rich (==13.7.1)
Requires-Dist: shellingham (==1.5.4)
Requires-Dist: textual (==0.63.4)
Requires-Dist: tomlkit (==0.12.5)
Requires-Dist: trove-classifiers (==2024.5.22)
Requires-Dist: twine (==5.1.0)
Requires-Dist: typing_extensions (==4.12.0)
Requires-Dist: uc-micro-py (==1.0.3)
Requires-Dist: urllib3 (==2.2.1)
Requires-Dist: virtualenv (==20.26.2)
